CHANGELOG.md
LICENSE
README.md
assets/shap_header.svg
shap_app/__init__.py
shap_app/__main__.py
shap_app/app/__init__.py
shap_app/app.py
shap_app/cli/__init__.py
shap_app/common/__init__.py
shap_app/common/enums/__init__.py
shap_app/configs/__init__.py
shap_app/configs/settings.py
shap_app/core/__init__.py
shap_app/core/celery/__init__.py
shap_app/core/celery/app.py
shap_app/core/celery/worker.py
shap_app/datasets/README.md
shap_app/datasets/__init__.py
shap_app/datasets/boston_housing/.gitignore
shap_app/datasets/boston_housing/__init__.py
shap_app/datasets/boston_housing/data_dictionary.py
shap_app/datasets/boston_housing/datasetcard.yml
shap_app/datasets/boston_housing/loader.py
shap_app/datasets/california_housing/.gitignore
shap_app/datasets/california_housing/README.md
shap_app/datasets/california_housing/__init__.py
shap_app/datasets/california_housing/california_housing.tgz
shap_app/datasets/california_housing/data_dictionary.py
shap_app/datasets/california_housing/datasetcard.yml
shap_app/datasets/california_housing/loader.py
shap_app/datasets/dataset_config.py
shap_app/datasets/sample_datasetcard.yml
shap_app/db/__init__.py
shap_app/io/__init__.py
shap_app/io/loaders.py
shap_app/main.py
shap_app/pipelines/__init__.py
shap_app/pipelines/boston_housing/__init__.py
shap_app/pipelines/boston_housing/transformation.py
shap_app/pipelines/california_housing/__init__.py
shap_app/pipelines/california_housing/transformation.py
shap_app/pipelines/pipeline_utils.py
shap_app/preprocessing/__init__.py
shap_app/preprocessing/binary.py
shap_app/preprocessing/categorical.py
shap_app/preprocessing/numerical.py
shap_app/trained_models/__init__.py
shap_app/trained_models/boston_housing/__init__.py
shap_app/trained_models/boston_housing/catboost_regressor.pkl
shap_app/trained_models/boston_housing/catboost_regressor.py
shap_app/trained_models/boston_housing/catboost_regressor_w_preprocessing.pkl
shap_app/trained_models/california_housing/__init__.py
shap_app-0.5.2.dist-info/LICENSE
shap_app-0.5.2.dist-info/METADATA
shap_app-0.5.2.dist-info/WHEEL
shap_app-0.5.2.dist-info/entry_points.txt
shap_app-0.5.2.dist-info/RECORD
