Metadata-Version: 2.1
Name: shap-app
Version: 0.5.2
Summary: A comprehensive application for interpreting machine learning models using SHAP values
License: MIT
Keywords: SHAP,Machine Learning,Model Interpretation,Python,Data Science,AI,Artificial Intelligence,Feature Importance,Game Theory,Predictive Modeling,Data Analysis,Modeling
Author: Rodrigo Gonzalez 
Author-email: r@rodrigo-gonzalez.com
Requires-Python: >=3.10,<3.12
Classifier: Development Status :: 4 - Beta
Classifier: Intended Audience :: Developers
Classifier: License :: OSI Approved :: MIT License
Classifier: Natural Language :: English
Classifier: Operating System :: OS Independent
Classifier: Programming Language :: Python :: 3
Classifier: Programming Language :: Python :: 3.10
Classifier: Programming Language :: Python :: 3.11
Classifier: Topic :: Scientific/Engineering :: Artificial Intelligence
Classifier: Topic :: Software Development :: Libraries :: Python Modules
Classifier: Typing :: Typed
Requires-Dist: altair (>=5.1.1,<6.0.0)
Requires-Dist: catboost (>=1.2.1,<2.0.0)
Requires-Dist: click (>=8.1.7,<9.0.0)
Requires-Dist: cmake (>=3.27.2,<4.0.0)
Requires-Dist: cython (>=3.0.2,<4.0.0)
Requires-Dist: feature-engine (>=1.6.1,<2.0.0)
Requires-Dist: joblib (>=1.3.2,<2.0.0)
Requires-Dist: lightgbm (>=4.0.0,<5.0.0)
Requires-Dist: llvmlite (>=0.40.1,<0.41.0)
Requires-Dist: matplotlib (>=3.7.2,<4.0.0)
Requires-Dist: numba (>=0.57.1,<0.58.0)
Requires-Dist: numpy (>=1.21,<1.25)
Requires-Dist: pandas (>=2.1.0,<3.0.0)
Requires-Dist: pdfkit (>=1.0.0,<2.0.0)
Requires-Dist: protobuf (>=4.24.2,<5.0.0)
Requires-Dist: pydantic (>=2.3.0,<3.0.0)
Requires-Dist: pydantic-settings (>=2.0.3,<3.0.0)
Requires-Dist: pydotenv (>=0.0.7,<0.0.8)
Requires-Dist: python-dotenv (>=1.0.0,<2.0.0)
Requires-Dist: scikit-learn (>=1.3.0,<2.0.0)
Requires-Dist: scipy (>=1.11.2,<2.0.0)
Requires-Dist: seaborn (>=0.12.2,<0.13.0)
Requires-Dist: setuptools (>=68.1.2,<69.0.0)
Requires-Dist: shap (>=0.42.1,<0.43.0)
Requires-Dist: statsmodels (>=0.14.0,<0.15.0)
Requires-Dist: streamlit (>=1.26.0,<2.0.0)
Requires-Dist: streamlit-aggrid (>=0.3.4.post3,<0.4.0)
Requires-Dist: streamlit-option-menu (>=0.3.6,<0.4.0)
Requires-Dist: streamlit-shap (>=1.0.2,<2.0.0)
Requires-Dist: streamlit-tags (>=1.2.8,<2.0.0)
Requires-Dist: strictyaml (>=1.7.3,<2.0.0)
Requires-Dist: typer (>=0.9.0,<0.10.0)
Requires-Dist: vega-datasets (>=0.9.0,<0.10.0)
Requires-Dist: xgboost (>=1.7.6,<2.0.0)
